descartkit/__init__.py
descartkit/llm/__init__.py
descartkit/llm/config/__init__.py
descartkit/llm/models/__init__.py
descartkit/llm/models/alibaba.py
descartkit/llm/models/anthropic.py
descartkit/llm/models/bedrock.py
descartkit/llm/models/deepseek.py
descartkit/llm/models/lingyi.py
descartkit/llm/models/moonshot.py
descartkit/llm/models/nvidia.py
descartkit/llm/models/ollama.py
descartkit/llm/models/openai.py
descartkit/llm/models/siliconflow.py
descartkit/llm/models/zhipu.py
descartkit/llm/moe/__init__.py
descartkit/llm/moe/router.py
descartkit/utils/__init__.py
descartkit/utils/file/__init__.py
descartkit/utils/file/handler.py
descartkit/utils/hash/__init__.py
descartkit/utils/http/HttpAsyncClient.py
descartkit/utils/http/HttpResult.py
descartkit/utils/http/__init__.py
descartkit/utils/security/__init__.py
descartkit/utils/security/aes.py
descartkit/utils/security/ecc.py
descartkit/utils/security/rsa.py
descartkit-2025.4.2.1.dist-info/LICENSE
descartkit-2025.4.2.1.dist-info/METADATA
descartkit-2025.4.2.1.dist-info/WHEEL
descartkit-2025.4.2.1.dist-info/top_level.txt
descartkit-2025.4.2.1.dist-info/RECORD
