Metadata-Version: 2.1
Name: descartkit
Version: 2025.4.2.1
Summary: A Python toolkit for advanced data processing and API interactions
Home-page: 
Author: DescartCan
Author-email: louishwh@gmail.com
Classifier: Programming Language :: Python :: 3
Classifier: License :: OSI Approved :: MIT License
Classifier: Operating System :: OS Independent
Requires-Python: >=3.10
License-File: LICENSE
Requires-Dist: aiohttp>=3.11.10
Requires-Dist: aiofiles~=24.1.0
Requires-Dist: loguru==0.6.0
Requires-Dist: openai~=1.58.1
Requires-Dist: anthropic~=0.42.0
Requires-Dist: boto3~=1.34.79
Requires-Dist: httpx==0.25.2
Requires-Dist: tiktoken==0.8.0
Requires-Dist: pyyaml~=6.0.2
